cmip_ref_metrics_example/__init__.py
cmip_ref_metrics_example/example.py
cmip_ref_metrics_example/py.typed
cmip_ref_metrics_example-0.4.0.dist-info/METADATA
cmip_ref_metrics_example-0.4.0.dist-info/WHEEL
cmip_ref_metrics_example-0.4.0.dist-info/licenses/LICENCE
cmip_ref_metrics_example-0.4.0.dist-info/licenses/NOTICE
cmip_ref_metrics_example-0.4.0.dist-info/RECORD
